{"version":1,"sessionId":"019f045c-dc2c-7f8b-92fa-90dff4c24f5a","savedAt":1782491356755,"widget":{"version":1,"sessionLanguages":[],"files":[{"filePath":"/home/lee/Documents/roid/scripts/PilotCharacter.gd","runners":[],"formatters":[],"diagnostics":[],"allDiagnostics":[],"diagnosticCounts":{"blocking":0,"errors":0,"warnings":0},"hasFinalDiagnosticsSnapshot":true,"touchedAt":1782487147128},{"filePath":"/home/lee/Documents/roid/scenes/HUD.tscn","runners":[],"formatters":[],"diagnostics":[],"allDiagnostics":[],"diagnosticCounts":{"blocking":0,"errors":0,"warnings":0},"hasFinalDiagnosticsSnapshot":true,"touchedAt":1782487178500},{"filePath":"/home/lee/Documents/roid/scripts/EnemyManager.gd","runners":[],"formatters":[],"diagnostics":[],"allDiagnostics":[],"diagnosticCounts":{"blocking":0,"errors":0,"warnings":0},"hasFinalDiagnosticsSnapshot":true,"touchedAt":1782487525492},{"filePath":"/home/lee/Documents/roid/scripts/BaseEnemy.gd","runners":[],"formatters":[],"diagnostics":[],"allDiagnostics":[],"diagnosticCounts":{"blocking":0,"errors":0,"warnings":0},"hasFinalDiagnosticsSnapshot":true,"touchedAt":1782487531482},{"filePath":"/home/lee/Documents/roid/scripts/enemies/ScoutDrone.gd","runners":[],"formatters":[],"diagnostics":[],"allDiagnostics":[],"diagnosticCounts":{"blocking":0,"errors":0,"warnings":0},"hasFinalDiagnosticsSnapshot":true,"touchedAt":1782487541154},{"filePath":"/home/lee/Documents/roid/scripts/enemies/HeavyGunship.gd","runners":[],"formatters":[],"diagnostics":[],"allDiagnostics":[],"diagnosticCounts":{"blocking":0,"errors":0,"warnings":0},"hasFinalDiagnosticsSnapshot":true,"touchedAt":1782487553423},{"filePath":"/home/lee/Documents/roid/scripts/enemies/MissileCruiser.gd","runners":[],"formatters":[],"diagnostics":[],"allDiagnostics":[],"diagnosticCounts":{"blocking":0,"errors":0,"warnings":0},"hasFinalDiagnosticsSnapshot":true,"touchedAt":1782487592962},{"filePath":"/home/lee/Documents/roid/scripts/HUD.gd","runners":[],"formatters":[],"diagnostics":[],"allDiagnostics":[],"diagnosticCounts":{"blocking":0,"errors":0,"warnings":0},"hasFinalDiagnosticsSnapshot":true,"touchedAt":1782491347941}]}}